README.md
setup.cfg
setup.py
pax2graphml/__init__.py
pax2graphml/clust.py
pax2graphml/extract.py
pax2graphml/graph_explore.py
pax2graphml/math.py
pax2graphml/pattern.py
pax2graphml/pax_import.py
pax2graphml/properties.py
pax2graphml/utils.py
pax2graphml.egg-info/PKG-INFO
pax2graphml.egg-info/SOURCES.txt
pax2graphml.egg-info/dependency_links.txt
pax2graphml.egg-info/not-zip-safe
pax2graphml.egg-info/requires.txt
pax2graphml.egg-info/top_level.txt
pax2graphml/data/G6P.owl
pax2graphml/resources/biopax2spaimgen.jar
pax2graphml/resources/graphml-v0.vm
pax2graphml/resources/graphml.vm
pax2graphml/resources/graphml_key.vm
pax2graphml/resources/simplegraphml.vm
test/test_pax2graphml.py