Metadata-Version: 2.1
Name: pax2graphml
Version: 1.0.2
Summary: A python library for large-scale regulation network analysis using BIOPAX and GRAPHML
Home-page: https://gitlab.inria.fr/fmoreews/pax2graphml
Author: FJR Moreews
Author-email: fjrmoreews@gmail.com
License: MIT
Platform: Posix; MacOS X;
Classifier: Development Status :: 4 - Beta
Classifier: Intended Audience :: Developers
Classifier: Intended Audience :: Science/Research
Classifier: License :: OSI Approved :: MIT License
Classifier: Programming Language :: Python :: 3.6
Classifier: Programming Language :: Python :: 3.7
Classifier: Programming Language :: Python :: 3.8
Classifier: Programming Language :: Python :: 3.9
Classifier: Topic :: Scientific/Engineering
Classifier: Topic :: Scientific/Engineering :: Bio-Informatics
Requires-Python: >=3.6.0
Provides-Extra: testing
